Metadata-Version: 2.1
Name: fast-norbert
Version: 1.0.1
Summary: Accelerated Wiener filter
Home-page: https://github.com/artyompal/fast_norbert
Author: Artyom Palvelev
License: UNKNOWN
Platform: UNKNOWN
